{
  "posts": [
    {
      "title": "신상 옷 팝니다!",
      "subtitle": "몇번안입었어요",
      "likes": 10,
      "price": 15000,
      "img": "/jsonimg/cloth2.jpeg",
      "date": "시",
      "location": "서울 강남구 개포로 416 1층",
      "category": 1,
      "id": 6
    },
    {
      "title": "입던옷팝니다 착샷있음",
      "subtitle": "ㅈㄱㄴ",
      "likes": 3,
      "price": 20000,
      "img": "/jsonimg/cloth1.jpeg",
      "date": "시",
      "location": "서울 강남구 개포로 416 1층",
      "category": 1,
      "id": 7
    },
    {
      "title": "옷 팜",
      "subtitle": "ㅈㄱㄴ",
      "likes": 1,
      "price": 15300,
      "img": "/jsonimg/cloth3.jpeg",
      "date": "2021-10-21 14시",
      "location": "서울 강남구 개포로 416 1층",
      "category": 1,
      "id": 8
    },
    {
      "title": "옷 ㅍㅍ",
      "subtitle": "ㅍㅍ",
      "likes": 4,
      "price": 23000,
      "img": "/jsonimg/test.jpeg.jpg",
      "date": "시",
      "location": "서울 강남구 개포로 416 1층",
      "category": 1,
      "id": 9
    },
    {
      "title": "옷입니당",
      "subtitle": "네",
      "likes": 7,
      "price": 2345,
      "img": "/jsonimg/cloth5.jpeg",
      "date": "시",
      "location": "서울 강남구 개포로 416 1층",
      "category": 1,
      "id": 10
    },
    {
      "title": "노트북 ㅍㅍ",
      "subtitle": "ㅍㅍ",
      "likes": 27,
      "price": 19,
      "img": "/jsonimg/it1.jpeg",
      "date": "시",
      "location": "서울 강남구 개포로 416 1층",
      "category": 2,
      "id": 11
    },
    {
      "id": 12,
      "title": "노트북 신형",
      "subtitle": "얼마전에 삿어요",
      "likes": 0,
      "price": 2000000,
      "img": "/jsonimg/it2.jpeg",
      "date": "2021-10-21T14:08:25+09:00",
      "location": "서울 강남구 개포로 416 1층",
      "category": 2
    },
    {
      "title": "맥북인지 삼성노트북인지 모르겠음",
      "subtitle": "직접판단하세요",
      "likes": 4,
      "price": 1234123,
      "img": "/jsonimg/it3.jpeg",
      "date": "시",
      "location": "서울 강남구 개포로 416 1층",
      "category": 2,
      "id": 13
    },
    {
      "title": "노트북",
      "subtitle": "ㅈㄱㄴ",
      "likes": 8,
      "price": 2345123,
      "img": "/jsonimg/it4.jpeg",
      "date": "시",
      "location": "서울 강남구 개포로 416 1층",
      "category": 2,
      "id": 14
    },
    {
      "id": 15,
      "title": "notebook",
      "subtitle": "ok",
      "likes": 0,
      "price": 3000000,
      "img": "/jsonimg/it5.jpeg",
      "date": "2021-10-21T14:08:25+09:00",
      "location": "서울 강남구 개포로 416 1층",
      "category": 2
    },
    {
      "title": "전자기기 팔아요",
      "subtitle": "ㅈㄱㄴ",
      "likes": 2,
      "price": 100000,
      "img": "/jsonimg/ex1.jpeg",
      "date": "2021-10-21 14시",
      "location": "서울 강남구 개포로 416 1층",
      "category": 3,
      "id": 16
    },
    {
      "id": 17,
      "title": "마우스 인듯?",
      "subtitle": "ㅇㅋ",
      "likes": 0,
      "price": 35000,
      "img": "/jsonimg/ex2.jpeg",
      "date": "2021-10-21T14:08:25+09:00",
      "location": "서울 강남구 개포로 416 1층",
      "category": 3
    },
    {
      "id": 18,
      "title": "거치대 였나",
      "subtitle": "모르곘네",
      "likes": 0,
      "price": 10000,
      "img": "/jsonimg/ex3.jpeg",
      "date": "2021-10-21T14:08:25+09:00",
      "location": "서울 강남구 개포로 416 1층",
      "category": 3
    },
    {
      "id": 19,
      "title": "이제 기억안나네",
      "subtitle": "진짜로",
      "likes": 0,
      "price": 5555,
      "img": "/jsonimg/ex4.jpeg",
      "date": "2021-10-21T14:08:25+09:00",
      "location": "서울 강남구 개포로 416 1층",
      "category": 3
    },
    {
      "id": 20,
      "title": "아이디어 고갈",
      "subtitle": "ㅇㅋ",
      "likes": 0,
      "price": 100000,
      "img": "/jsonimg/ex5.jpeg",
      "date": "2021-10-21T14:08:25+09:00",
      "location": "서울 강남구 개포로 416 1층",
      "category": 3
    },
    {
      "id": 21,
      "title": "인생책팝니다",
      "subtitle": "꼭보세요",
      "likes": 0,
      "price": 15000,
      "img": "/jsonimg/book1.jpeg",
      "date": "2021-10-21T14:08:25+09:00",
      "location": "서울 강남구 개포로 416 1층",
      "category": 4
    },
    {
      "id": 22,
      "title": "좋은책들 팜",
      "subtitle": "ㅈㄱㄴ",
      "likes": 0,
      "price": 30000,
      "img": "/jsonimg/book2.jpeg",
      "date": "2021-10-21T14:08:25+09:00",
      "location": "서울 강남구 개포로 416 1층",
      "category": 4
    },
    {
      "id": 23,
      "title": "책책책 책을 읽읍시다!",
      "subtitle": "ㅈㄱㄴ",
      "likes": 0,
      "price": 100004,
      "img": "/jsonimg/book3.jpeg",
      "date": "2021-10-21T14:08:25+09:00",
      "location": "서울 강남구 개포로 416 1층",
      "category": 4
    },
    {
      "id": 24,
      "title": "책",
      "subtitle": "팜",
      "likes": 0,
      "price": 15000,
      "img": "/jsonimg/book4.jpeg",
      "date": "2021-10-21T14:08:25+09:00",
      "location": "서울 강남구 개포로 416 1층",
      "category": 4
    },
    {
      "id": 25,
      "title": "책책",
      "subtitle": "책책",
      "likes": 0,
      "price": 234,
      "img": "/jsonimg/book5.jpeg",
      "date": "2021-10-21T14:08:25+09:00",
      "location": "서울 강남구 개포로 416 1층",
      "category": 4
    },
    {
      "title": "책을 읽는 사람들 팝니다!",
      "subtitle": "재밌게 읽었는데 다른책 구매하려고 팝니다.",
      "price": 12345,
      "likes": 0,
      "category": 4,
      "location": "서울 서초구 강남대로 327 대륭서초타워 ",
      "img": "/jsonimg/book5.jpeg",
      "date": "2021-10-21T14:08:25+09:00",
      "id": 26
    },
    {
      "title": "책을 읽어볼까요? 재미없어서 팝니다.",
      "subtitle": "읽다가 재미없어서 거래합니다.",
      "likes": 3,
      "price": 100500,
      "img": "/jsonimg/book5.jpeg",
      "date": "시",
      "location": "서울 강남구 개포로 416 지하3층 바로 지금!",
      "category": 4,
      "id": 27
    }
  ],
  "comments": [
    {
      "id": 1,
      "body": "some comment",
      "postId": 1
    },
    {
      "id": 2
    },
    {
      "id": 3
    },
    {
      "id": 4
    },
    {
      "id": 5
    },
    {
      "id": 6
    },
    {
      "id": 7
    },
    {
      "id": 8
    },
    {
      "id": 9
    },
    {
      "id": 10
    },
    {
      "id": 11
    },
    {
      "id": 12
    },
    {
      "id": 13
    },
    {
      "id": 14
    },
    {
      "id": 15
    },
    {
      "id": 16
    },
    {
      "id": 17
    },
    {
      "id": 18
    }
  ],
  "data": [
    {
      "id": 1
    },
    {
      "id": 2
    },
    {
      "id": 3
    },
    {
      "id": 4
    },
    {
      "id": 5
    },
    {
      "id": 6
    },
    {
      "id": 7
    },
    {
      "id": 8
    },
    {
      "id": 9
    },
    {
      "id": 10
    },
    {
      "id": 11
    },
    {
      "id": 12
    },
    {
      "id": 13
    },
    {
      "id": 14
    },
    {
      "id": 15
    },
    {
      "id": 16
    }
  ],
  "profile": {
    "name": "typicode"
  }
}